germanetpy/__init__.py
germanetpy/compoundInfo.py
germanetpy/filterconfig.py
germanetpy/frames.py
germanetpy/germanet.py
germanetpy/icbased_similarity.py
germanetpy/iliLoader.py
germanetpy/iliRecord.py
germanetpy/lexunit.py
germanetpy/longest_shortest_path.py
germanetpy/path_based_relatedness_measures.py
germanetpy/relationLoader.py
germanetpy/semrel_measures.py
germanetpy/synset.py
germanetpy/synsetLoader.py
germanetpy/utils.py
germanetpy/wiktionaryLoader.py
germanetpy/wiktionaryparaphrase.py
germanetpy-0.2.5.dist-info/licenses/LICENSE
germanetpy-0.2.5.dist-info/METADATA
germanetpy-0.2.5.dist-info/WHEEL
germanetpy-0.2.5.dist-info/top_level.txt
germanetpy-0.2.5.dist-info/RECORD
