Metadata-Version: 2.4
Name: germanetpy
Version: 0.2.5
Summary: Python API for GermaNet
Home-page: https://github.com/Germanet-sfs/germanetpy.git
Author: Ben Campbell
Author-email: ben.campbell@uni-tuebingen.de
Classifier: Programming Language :: Python :: 3
Classifier: Programming Language :: Python :: 3.12
Classifier: License :: OSI Approved :: Apache Software License
Classifier: Operating System :: OS Independent
License-File: LICENSE
Requires-Dist: numpy>=1.18.1
Requires-Dist: lxml>=4.4.2
Requires-Dist: pytest>=5.3.2
Requires-Dist: fastenum>=0.0.1
Requires-Dist: tqdm>=4.14
Requires-Dist: python-Levenshtein==0.27.3
Dynamic: author
Dynamic: author-email
Dynamic: classifier
Dynamic: description
Dynamic: description-content-type
Dynamic: home-page
Dynamic: license-file
Dynamic: requires-dist
Dynamic: summary
